odoo/addons/project_mail_chatter/README.rst
odoo/addons/project_mail_chatter/__init__.py
odoo/addons/project_mail_chatter/__manifest__.py
odoo/addons/project_mail_chatter/i18n/it.po
odoo/addons/project_mail_chatter/i18n/project_mail_chatter.pot
odoo/addons/project_mail_chatter/i18n/pt_BR.po
odoo/addons/project_mail_chatter/readme/CONTRIBUTORS.rst
odoo/addons/project_mail_chatter/readme/CREDITS.rst
odoo/addons/project_mail_chatter/readme/DESCRIPTION.rst
odoo/addons/project_mail_chatter/static/description/icon.png
odoo/addons/project_mail_chatter/static/description/index.html
odoo/addons/project_mail_chatter/views/project_view.xml
odoo12_addon_project_mail_chatter-12.0.1.0.0.99.dev7.dist-info/METADATA
odoo12_addon_project_mail_chatter-12.0.1.0.0.99.dev7.dist-info/WHEEL
odoo12_addon_project_mail_chatter-12.0.1.0.0.99.dev7.dist-info/top_level.txt
odoo12_addon_project_mail_chatter-12.0.1.0.0.99.dev7.dist-info/RECORD
